{
  "current": {
    "number": 94,
    "timestamp": 1762340328,
    "type": "gain",
    "variant": "normal"
  },
  "total": {
    "loss": 195,
    "gain": 444,
    "loss_count": 1285,
    "gain_count": 1929,
    "calculation": 33231
  },
  "old": [
    {
      "number": 28,
      "timestamp": 1762319759,
      "type": "gain",
      "variant": "normal",
      "calculation": 33010
    },
    {
      "number": 20,
      "timestamp": 1762320887,
      "type": "gain",
      "variant": "normal",
      "calculation": 33030
    },
    {
      "number": 56,
      "timestamp": 1762321535,
      "type": "loss",
      "variant": "volatile",
      "calculation": 32974
    },
    {
      "number": 9,
      "timestamp": 1762322379,
      "type": "gain",
      "variant": "normal",
      "calculation": 32983
    },
    {
      "number": 14,
      "timestamp": 1762324438,
      "type": "gain",
      "variant": "normal",
      "calculation": 32997
    },
    {
      "number": 89,
      "timestamp": 1762325571,
      "type": "gain",
      "variant": "normal",
      "calculation": 33086
    },
    {
      "number": 62,
      "timestamp": 1762325980,
      "type": "gain",
      "variant": "normal",
      "calculation": 33148
    },
    {
      "number": 44,
      "timestamp": 1762327303,
      "type": "loss",
      "variant": "normal",
      "calculation": 33104
    },
    {
      "number": 82,
      "timestamp": 1762328024,
      "type": "loss",
      "variant": "normal",
      "calculation": 33022
    },
    {
      "number": 12,
      "timestamp": 1762336200,
      "type": "gain",
      "variant": "normal",
      "calculation": 33034
    },
    {
      "number": 42,
      "timestamp": 1762336619,
      "type": "gain",
      "variant": "volatile",
      "calculation": 33076
    },
    {
      "number": 74,
      "timestamp": 1762337920,
      "type": "gain",
      "variant": "normal",
      "calculation": 33150
    },
    {
      "number": 13,
      "timestamp": 1762339262,
      "type": "loss",
      "variant": "normal",
      "calculation": 33137
    }
  ]
}
