{
  "current": {
    "number": 75,
    "timestamp": 1757556872,
    "type": "loss",
    "variant": "volatile"
  },
  "total": {
    "loss": 743,
    "gain": 1951,
    "loss_count": 141,
    "gain_count": 210,
    "calculation": 3369
  },
  "old": [
    {
      "number": 90,
      "timestamp": 1757454235,
      "type": "gain",
      "variant": "volatile",
      "calculation": 2251
    },
    {
      "number": 4,
      "timestamp": 1757456991,
      "type": "gain",
      "variant": "normal",
      "calculation": 2255
    },
    {
      "number": 2,
      "timestamp": 1757458805,
      "type": "loss",
      "variant": "normal",
      "calculation": 2253
    },
    {
      "number": 59,
      "timestamp": 1757459951,
      "type": "gain",
      "variant": "normal",
      "calculation": 2312
    },
    {
      "number": 89,
      "timestamp": 1757461027,
      "type": "gain",
      "variant": "normal",
      "calculation": 2401
    },
    {
      "number": 51,
      "timestamp": 1757461894,
      "type": "gain",
      "variant": "normal",
      "calculation": 2452
    },
    {
      "number": 64,
      "timestamp": 1757462330,
      "type": "loss",
      "variant": "normal",
      "calculation": 2388
    },
    {
      "number": 78,
      "timestamp": 1757471820,
      "type": "gain",
      "variant": "normal",
      "calculation": 2466
    },
    {
      "number": 10,
      "timestamp": 1757476494,
      "type": "gain",
      "variant": "normal",
      "calculation": 2476
    },
    {
      "number": 66,
      "timestamp": 1757478700,
      "type": "loss",
      "variant": "normal",
      "calculation": 2410
    },
    {
      "number": 35,
      "timestamp": 1757479762,
      "type": "loss",
      "variant": "normal",
      "calculation": 2375
    },
    {
      "number": 21,
      "timestamp": 1757480186,
      "type": "loss",
      "variant": "normal",
      "calculation": 2354
    },
    {
      "number": 58,
      "timestamp": 1757482226,
      "type": "gain",
      "variant": "normal",
      "calculation": 2412
    },
    {
      "number": 50,
      "timestamp": 1757482864,
      "type": "loss",
      "variant": "volatile",
      "calculation": 2362
    },
    {
      "number": 33,
      "timestamp": 1757483715,
      "type": "loss",
      "variant": "normal",
      "calculation": 2329
    },
    {
      "number": 52,
      "timestamp": 1757488890,
      "type": "gain",
      "variant": "normal",
      "calculation": 2381
    },
    {
      "number": 35,
      "timestamp": 1757492037,
      "type": "gain",
      "variant": "normal",
      "calculation": 2416
    },
    {
      "number": 85,
      "timestamp": 1757497334,
      "type": "loss",
      "variant": "volatile",
      "calculation": 2331
    },
    {
      "number": 68,
      "timestamp": 1757500378,
      "type": "gain",
      "variant": "normal",
      "calculation": 2399
    },
    {
      "number": 33,
      "timestamp": 1757501453,
      "type": "loss",
      "variant": "normal",
      "calculation": 2366
    },
    {
      "number": 86,
      "timestamp": 1757504037,
      "type": "gain",
      "variant": "normal",
      "calculation": 2452
    },
    {
      "number": 46,
      "timestamp": 1757504464,
      "type": "gain",
      "variant": "normal",
      "calculation": 2498
    },
    {
      "number": 9,
      "timestamp": 1757505343,
      "type": "loss",
      "variant": "normal",
      "calculation": 2489
    },
    {
      "number": 3,
      "timestamp": 1757512175,
      "type": "gain",
      "variant": "normal",
      "calculation": 2492
    },
    {
      "number": 88,
      "timestamp": 1757512596,
      "type": "loss",
      "variant": "normal",
      "calculation": 2404
    },
    {
      "number": 25,
      "timestamp": 1757514715,
      "type": "gain",
      "variant": "volatile",
      "calculation": 2429
    },
    {
      "number": 7,
      "timestamp": 1757515852,
      "type": "gain",
      "variant": "normal",
      "calculation": 2436
    },
    {
      "number": 97,
      "timestamp": 1757518357,
      "type": "gain",
      "variant": "volatile",
      "calculation": 2533
    },
    {
      "number": 31,
      "timestamp": 1757518958,
      "type": "gain",
      "variant": "normal",
      "calculation": 2564
    },
    {
      "number": 18,
      "timestamp": 1757522405,
      "type": "gain",
      "variant": "volatile",
      "calculation": 2582
    },
    {
      "number": 75,
      "timestamp": 1757523050,
      "type": "gain",
      "variant": "normal",
      "calculation": 2657
    },
    {
      "number": 29,
      "timestamp": 1757525898,
      "type": "loss",
      "variant": "normal",
      "calculation": 2628
    },
    {
      "number": 52,
      "timestamp": 1757526321,
      "type": "gain",
      "variant": "normal",
      "calculation": 2680
    },
    {
      "number": 89,
      "timestamp": 1757528970,
      "type": "gain",
      "variant": "volatile",
      "calculation": 2769
    },
    {
      "number": 57,
      "timestamp": 1757530488,
      "type": "gain",
      "variant": "normal",
      "calculation": 2826
    },
    {
      "number": 40,
      "timestamp": 1757531282,
      "type": "gain",
      "variant": "volatile",
      "calculation": 2866
    },
    {
      "number": 57,
      "timestamp": 1757532508,
      "type": "loss",
      "variant": "normal",
      "calculation": 2809
    },
    {
      "number": 75,
      "timestamp": 1757533031,
      "type": "loss",
      "variant": "normal",
      "calculation": 2734
    },
    {
      "number": 87,
      "timestamp": 1757535555,
      "type": "gain",
      "variant": "volatile",
      "calculation": 2821
    },
    {
      "number": 53,
      "timestamp": 1757536401,
      "type": "gain",
      "variant": "normal",
      "calculation": 2874
    },
    {
      "number": 65,
      "timestamp": 1757537431,
      "type": "gain",
      "variant": "volatile",
      "calculation": 2939
    },
    {
      "number": 11,
      "timestamp": 1757537857,
      "type": "gain",
      "variant": "normal",
      "calculation": 2950
    },
    {
      "number": 70,
      "timestamp": 1757538891,
      "type": "gain",
      "variant": "normal",
      "calculation": 3020
    },
    {
      "number": 6,
      "timestamp": 1757539617,
      "type": "gain",
      "variant": "normal",
      "calculation": 3026
    },
    {
      "number": 21,
      "timestamp": 1757540566,
      "type": "loss",
      "variant": "normal",
      "calculation": 3005
    },
    {
      "number": 89,
      "timestamp": 1757542479,
      "type": "gain",
      "variant": "normal",
      "calculation": 3094
    },
    {
      "number": 85,
      "timestamp": 1757545800,
      "type": "gain",
      "variant": "volatile",
      "calculation": 3179
    },
    {
      "number": 100,
      "timestamp": 1757546685,
      "type": "gain",
      "variant": "volatile",
      "calculation": 3279
    },
    {
      "number": 84,
      "timestamp": 1757547617,
      "type": "gain",
      "variant": "normal",
      "calculation": 3363
    },
    {
      "number": 81,
      "timestamp": 1757548048,
      "type": "gain",
      "variant": "normal",
      "calculation": 3444
    }
  ]
}
