{
  "current": {
    "number": 145,
    "timestamp": 1745876910,
    "type": "loss",
    "variant": "volatile"
  },
  "total": {
    "loss": 268,
    "gain": 507,
    "loss_count": 739,
    "gain_count": 1072,
    "calculation": 24449
  },
  "old": [
    {
      "number": 3,
      "timestamp": 1745865172,
      "type": "gain",
      "variant": "normal",
      "calculation": 24213
    },
    {
      "number": 5,
      "timestamp": 1745866175,
      "type": "gain",
      "variant": "normal",
      "calculation": 24218
    },
    {
      "number": 32,
      "timestamp": 1745869613,
      "type": "loss",
      "variant": "normal",
      "calculation": 24186
    },
    {
      "number": 109,
      "timestamp": 1745870050,
      "type": "gain",
      "variant": "volatile",
      "calculation": 24295
    },
    {
      "number": 91,
      "timestamp": 1745872754,
      "type": "loss",
      "variant": "normal",
      "calculation": 24204
    },
    {
      "number": 102,
      "timestamp": 1745873185,
      "type": "gain",
      "variant": "normal",
      "calculation": 24306
    },
    {
      "number": 17,
      "timestamp": 1745873614,
      "type": "gain",
      "variant": "normal",
      "calculation": 24323
    },
    {
      "number": 63,
      "timestamp": 1745874411,
      "type": "gain",
      "variant": "volatile",
      "calculation": 24386
    },
    {
      "number": 125,
      "timestamp": 1745875467,
      "type": "gain",
      "variant": "normal",
      "calculation": 24511
    },
    {
      "number": 83,
      "timestamp": 1745876053,
      "type": "gain",
      "variant": "normal",
      "calculation": 24594
    }
  ]
}
