{
  "current": {
    "number": 5,
    "timestamp": 1743376053,
    "type": "loss",
    "variant": "volatile"
  },
  "total": {
    "loss": 74,
    "gain": 312,
    "loss_count": 48,
    "gain_count": 166,
    "calculation": 2629
  },
  "old": [
    {
      "number": 17,
      "timestamp": 1743331817,
      "type": "gain",
      "variant": "normal",
      "calculation": 2408
    },
    {
      "number": 25,
      "timestamp": 1743339109,
      "type": "gain",
      "variant": "volatile",
      "calculation": 2433
    },
    {
      "number": 26,
      "timestamp": 1743342395,
      "type": "gain",
      "variant": "normal",
      "calculation": 2459
    },
    {
      "number": 42,
      "timestamp": 1743343519,
      "type": "gain",
      "variant": "normal",
      "calculation": 2501
    },
    {
      "number": 21,
      "timestamp": 1743353390,
      "type": "gain",
      "variant": "normal",
      "calculation": 2522
    },
    {
      "number": 34,
      "timestamp": 1743353827,
      "type": "gain",
      "variant": "normal",
      "calculation": 2556
    },
    {
      "number": 21,
      "timestamp": 1743355710,
      "type": "gain",
      "variant": "normal",
      "calculation": 2577
    },
    {
      "number": 32,
      "timestamp": 1743359043,
      "type": "gain",
      "variant": "normal",
      "calculation": 2609
    },
    {
      "number": 32,
      "timestamp": 1743360961,
      "type": "gain",
      "variant": "volatile",
      "calculation": 2641
    },
    {
      "number": 33,
      "timestamp": 1743363854,
      "type": "loss",
      "variant": "normal",
      "calculation": 2608
    },
    {
      "number": 36,
      "timestamp": 1743367724,
      "type": "loss",
      "variant": "volatile",
      "calculation": 2572
    },
    {
      "number": 36,
      "timestamp": 1743373775,
      "type": "gain",
      "variant": "normal",
      "calculation": 2608
    },
    {
      "number": 26,
      "timestamp": 1743374815,
      "type": "gain",
      "variant": "volatile",
      "calculation": 2634
    }
  ]
}
