{
  "current": {
    "number": 44,
    "timestamp": 1754459400,
    "type": "loss",
    "variant": "normal"
  },
  "total": {
    "loss": 44,
    "gain": 74,
    "loss_count": 731,
    "gain_count": 2873,
    "calculation": 52534
  },
  "old": [
    {
      "number": 10,
      "timestamp": 1754437566,
      "type": "gain",
      "variant": "normal",
      "calculation": 52514
    },
    {
      "number": 27,
      "timestamp": 1754456018,
      "type": "gain",
      "variant": "normal",
      "calculation": 52541
    },
    {
      "number": 37,
      "timestamp": 1754457682,
      "type": "gain",
      "variant": "normal",
      "calculation": 52578
    }
  ]
}
