{
  "current": {
    "number": 18,
    "timestamp": 1746251408,
    "type": "gain",
    "variant": "normal"
  },
  "total": {
    "loss": 0,
    "gain": 113,
    "loss_count": 247,
    "gain_count": 957,
    "calculation": 17187
  },
  "old": [
    {
      "number": 48,
      "timestamp": 1746229604,
      "type": "gain",
      "variant": "normal",
      "calculation": 17122
    },
    {
      "number": 42,
      "timestamp": 1746243831,
      "type": "gain",
      "variant": "volatile",
      "calculation": 17164
    },
    {
      "number": 5,
      "timestamp": 1746250318,
      "type": "gain",
      "variant": "volatile",
      "calculation": 17169
    }
  ]
}
