{
  "current": {
    "number": 18,
    "timestamp": 1760290935,
    "type": "gain",
    "variant": "volatile"
  },
  "total": {
    "loss": 7,
    "gain": 106,
    "loss_count": 220,
    "gain_count": 986,
    "calculation": 36930
  },
  "old": [
    {
      "number": 7,
      "timestamp": 1760280969,
      "type": "loss",
      "variant": "normal",
      "calculation": 36824
    },
    {
      "number": 32,
      "timestamp": 1760283278,
      "type": "gain",
      "variant": "volatile",
      "calculation": 36856
    },
    {
      "number": 38,
      "timestamp": 1760285617,
      "type": "gain",
      "variant": "normal",
      "calculation": 36894
    },
    {
      "number": 15,
      "timestamp": 1760289170,
      "type": "gain",
      "variant": "normal",
      "calculation": 36909
    },
    {
      "number": 3,
      "timestamp": 1760290008,
      "type": "gain",
      "variant": "normal",
      "calculation": 36912
    }
  ]
}
