{
  "current": {
    "number": 30,
    "timestamp": 1757274261,
    "type": "gain",
    "variant": "normal"
  },
  "total": {
    "loss": 187,
    "gain": 552,
    "loss_count": 18,
    "gain_count": 95,
    "calculation": 4193
  },
  "old": [
    {
      "number": 40,
      "timestamp": 1757252504,
      "type": "gain",
      "variant": "normal",
      "calculation": 3868
    },
    {
      "number": 30,
      "timestamp": 1757254223,
      "type": "loss",
      "variant": "volatile",
      "calculation": 3838
    },
    {
      "number": 89,
      "timestamp": 1757255194,
      "type": "gain",
      "variant": "normal",
      "calculation": 3927
    },
    {
      "number": 76,
      "timestamp": 1757256587,
      "type": "gain",
      "variant": "normal",
      "calculation": 4003
    },
    {
      "number": 96,
      "timestamp": 1757259252,
      "type": "gain",
      "variant": "volatile",
      "calculation": 4099
    },
    {
      "number": 35,
      "timestamp": 1757260113,
      "type": "gain",
      "variant": "normal",
      "calculation": 4134
    },
    {
      "number": 99,
      "timestamp": 1757260545,
      "type": "loss",
      "variant": "volatile",
      "calculation": 4035
    },
    {
      "number": 58,
      "timestamp": 1757262747,
      "type": "loss",
      "variant": "normal",
      "calculation": 3977
    },
    {
      "number": 17,
      "timestamp": 1757263381,
      "type": "gain",
      "variant": "volatile",
      "calculation": 3994
    },
    {
      "number": 3,
      "timestamp": 1757266804,
      "type": "gain",
      "variant": "normal",
      "calculation": 3997
    },
    {
      "number": 87,
      "timestamp": 1757267228,
      "type": "gain",
      "variant": "normal",
      "calculation": 4084
    },
    {
      "number": 79,
      "timestamp": 1757270686,
      "type": "gain",
      "variant": "volatile",
      "calculation": 4163
    }
  ]
}
