{
  "current": {
    "number": 4,
    "timestamp": 1752074325,
    "type": "gain",
    "variant": "volatile"
  },
  "total": {
    "loss": 439,
    "gain": 1708,
    "loss_count": 611,
    "gain_count": 2376,
    "calculation": 43361
  },
  "old": [
    {
      "number": 47,
      "timestamp": 1751737165,
      "type": "gain",
      "variant": "normal",
      "calculation": 42139
    },
    {
      "number": 47,
      "timestamp": 1751743478,
      "type": "gain",
      "variant": "volatile",
      "calculation": 42186
    },
    {
      "number": 24,
      "timestamp": 1751759045,
      "type": "loss",
      "variant": "normal",
      "calculation": 42162
    },
    {
      "number": 32,
      "timestamp": 1751759458,
      "type": "gain",
      "variant": "volatile",
      "calculation": 42194
    },
    {
      "number": 42,
      "timestamp": 1751766213,
      "type": "gain",
      "variant": "normal",
      "calculation": 42236
    },
    {
      "number": 32,
      "timestamp": 1751774657,
      "type": "gain",
      "variant": "volatile",
      "calculation": 42268
    },
    {
      "number": 30,
      "timestamp": 1751776808,
      "type": "gain",
      "variant": "normal",
      "calculation": 42298
    },
    {
      "number": 9,
      "timestamp": 1751782462,
      "type": "gain",
      "variant": "normal",
      "calculation": 42307
    },
    {
      "number": 9,
      "timestamp": 1751784926,
      "type": "gain",
      "variant": "volatile",
      "calculation": 42316
    },
    {
      "number": 10,
      "timestamp": 1751785905,
      "type": "gain",
      "variant": "volatile",
      "calculation": 42326
    },
    {
      "number": 18,
      "timestamp": 1751786861,
      "type": "loss",
      "variant": "volatile",
      "calculation": 42308
    },
    {
      "number": 8,
      "timestamp": 1751788282,
      "type": "gain",
      "variant": "volatile",
      "calculation": 42316
    },
    {
      "number": 7,
      "timestamp": 1751790197,
      "type": "loss",
      "variant": "normal",
      "calculation": 42309
    },
    {
      "number": 31,
      "timestamp": 1751794557,
      "type": "gain",
      "variant": "volatile",
      "calculation": 42340
    },
    {
      "number": 44,
      "timestamp": 1751801216,
      "type": "loss",
      "variant": "normal",
      "calculation": 42296
    },
    {
      "number": 25,
      "timestamp": 1751802695,
      "type": "gain",
      "variant": "volatile",
      "calculation": 42321
    },
    {
      "number": 0,
      "timestamp": 1751809609,
      "type": "loss",
      "variant": "normal",
      "calculation": 42321
    },
    {
      "number": 37,
      "timestamp": 1751816385,
      "type": "gain",
      "variant": "normal",
      "calculation": 42358
    },
    {
      "number": 42,
      "timestamp": 1751817298,
      "type": "gain",
      "variant": "normal",
      "calculation": 42400
    },
    {
      "number": 12,
      "timestamp": 1751818374,
      "type": "gain",
      "variant": "normal",
      "calculation": 42412
    },
    {
      "number": 29,
      "timestamp": 1751820723,
      "type": "gain",
      "variant": "normal",
      "calculation": 42441
    },
    {
      "number": 22,
      "timestamp": 1751824269,
      "type": "loss",
      "variant": "volatile",
      "calculation": 42419
    },
    {
      "number": 28,
      "timestamp": 1751824687,
      "type": "gain",
      "variant": "normal",
      "calculation": 42447
    },
    {
      "number": 35,
      "timestamp": 1751826275,
      "type": "gain",
      "variant": "normal",
      "calculation": 42482
    },
    {
      "number": 43,
      "timestamp": 1751830221,
      "type": "gain",
      "variant": "volatile",
      "calculation": 42525
    },
    {
      "number": 24,
      "timestamp": 1751835557,
      "type": "loss",
      "variant": "volatile",
      "calculation": 42501
    },
    {
      "number": 23,
      "timestamp": 1751836757,
      "type": "gain",
      "variant": "volatile",
      "calculation": 42524
    },
    {
      "number": 17,
      "timestamp": 1751842023,
      "type": "gain",
      "variant": "normal",
      "calculation": 42541
    },
    {
      "number": 3,
      "timestamp": 1751860697,
      "type": "gain",
      "variant": "normal",
      "calculation": 42544
    },
    {
      "number": 37,
      "timestamp": 1751866914,
      "type": "gain",
      "variant": "normal",
      "calculation": 42581
    },
    {
      "number": 9,
      "timestamp": 1751874300,
      "type": "loss",
      "variant": "normal",
      "calculation": 42572
    },
    {
      "number": 6,
      "timestamp": 1751881713,
      "type": "gain",
      "variant": "normal",
      "calculation": 42578
    },
    {
      "number": 16,
      "timestamp": 1751888234,
      "type": "gain",
      "variant": "normal",
      "calculation": 42594
    },
    {
      "number": 1,
      "timestamp": 1751888725,
      "type": "gain",
      "variant": "normal",
      "calculation": 42595
    },
    {
      "number": 48,
      "timestamp": 1751892296,
      "type": "loss",
      "variant": "volatile",
      "calculation": 42547
    },
    {
      "number": 29,
      "timestamp": 1751894547,
      "type": "gain",
      "variant": "volatile",
      "calculation": 42576
    },
    {
      "number": 42,
      "timestamp": 1751907474,
      "type": "gain",
      "variant": "normal",
      "calculation": 42618
    },
    {
      "number": 8,
      "timestamp": 1751908599,
      "type": "loss",
      "variant": "normal",
      "calculation": 42610
    },
    {
      "number": 47,
      "timestamp": 1751918066,
      "type": "gain",
      "variant": "normal",
      "calculation": 42657
    },
    {
      "number": 41,
      "timestamp": 1751920421,
      "type": "gain",
      "variant": "volatile",
      "calculation": 42698
    },
    {
      "number": 15,
      "timestamp": 1751924822,
      "type": "gain",
      "variant": "normal",
      "calculation": 42713
    },
    {
      "number": 45,
      "timestamp": 1751926151,
      "type": "gain",
      "variant": "normal",
      "calculation": 42758
    },
    {
      "number": 3,
      "timestamp": 1751929180,
      "type": "gain",
      "variant": "normal",
      "calculation": 42761
    },
    {
      "number": 20,
      "timestamp": 1751947094,
      "type": "gain",
      "variant": "normal",
      "calculation": 42781
    },
    {
      "number": 35,
      "timestamp": 1751948969,
      "type": "gain",
      "variant": "normal",
      "calculation": 42816
    },
    {
      "number": 16,
      "timestamp": 1751952424,
      "type": "gain",
      "variant": "normal",
      "calculation": 42832
    },
    {
      "number": 24,
      "timestamp": 1751953958,
      "type": "gain",
      "variant": "normal",
      "calculation": 42856
    },
    {
      "number": 50,
      "timestamp": 1751959889,
      "type": "loss",
      "variant": "normal",
      "calculation": 42806
    },
    {
      "number": 5,
      "timestamp": 1751960633,
      "type": "gain",
      "variant": "volatile",
      "calculation": 42811
    },
    {
      "number": 35,
      "timestamp": 1751965278,
      "type": "loss",
      "variant": "normal",
      "calculation": 42776
    },
    {
      "number": 18,
      "timestamp": 1751968412,
      "type": "loss",
      "variant": "volatile",
      "calculation": 42758
    },
    {
      "number": 0,
      "timestamp": 1751970953,
      "type": "gain",
      "variant": "normal",
      "calculation": 42758
    },
    {
      "number": 10,
      "timestamp": 1751971831,
      "type": "gain",
      "variant": "normal",
      "calculation": 42768
    },
    {
      "number": 8,
      "timestamp": 1751972243,
      "type": "gain",
      "variant": "normal",
      "calculation": 42776
    },
    {
      "number": 37,
      "timestamp": 1751973339,
      "type": "gain",
      "variant": "volatile",
      "calculation": 42813
    },
    {
      "number": 18,
      "timestamp": 1751974188,
      "type": "gain",
      "variant": "volatile",
      "calculation": 42831
    },
    {
      "number": 32,
      "timestamp": 1751974889,
      "type": "gain",
      "variant": "normal",
      "calculation": 42863
    },
    {
      "number": 19,
      "timestamp": 1751977623,
      "type": "gain",
      "variant": "normal",
      "calculation": 42882
    },
    {
      "number": 48,
      "timestamp": 1751980051,
      "type": "gain",
      "variant": "volatile",
      "calculation": 42930
    },
    {
      "number": 32,
      "timestamp": 1751982308,
      "type": "gain",
      "variant": "normal",
      "calculation": 42962
    },
    {
      "number": 22,
      "timestamp": 1751986287,
      "type": "loss",
      "variant": "normal",
      "calculation": 42940
    },
    {
      "number": 14,
      "timestamp": 1751991756,
      "type": "gain",
      "variant": "normal",
      "calculation": 42954
    },
    {
      "number": 42,
      "timestamp": 1751993158,
      "type": "loss",
      "variant": "normal",
      "calculation": 42912
    },
    {
      "number": 22,
      "timestamp": 1751993943,
      "type": "gain",
      "variant": "volatile",
      "calculation": 42934
    },
    {
      "number": 5,
      "timestamp": 1751998877,
      "type": "gain",
      "variant": "normal",
      "calculation": 42939
    },
    {
      "number": 14,
      "timestamp": 1752002220,
      "type": "loss",
      "variant": "volatile",
      "calculation": 42925
    },
    {
      "number": 9,
      "timestamp": 1752002951,
      "type": "gain",
      "variant": "normal",
      "calculation": 42934
    },
    {
      "number": 23,
      "timestamp": 1752003514,
      "type": "gain",
      "variant": "normal",
      "calculation": 42957
    },
    {
      "number": 10,
      "timestamp": 1752004363,
      "type": "loss",
      "variant": "normal",
      "calculation": 42947
    },
    {
      "number": 23,
      "timestamp": 1752006358,
      "type": "gain",
      "variant": "volatile",
      "calculation": 42970
    },
    {
      "number": 31,
      "timestamp": 1752008343,
      "type": "gain",
      "variant": "normal",
      "calculation": 43001
    },
    {
      "number": 20,
      "timestamp": 1752018250,
      "type": "gain",
      "variant": "normal",
      "calculation": 43021
    },
    {
      "number": 45,
      "timestamp": 1752025275,
      "type": "gain",
      "variant": "normal",
      "calculation": 43066
    },
    {
      "number": 24,
      "timestamp": 1752035984,
      "type": "loss",
      "variant": "normal",
      "calculation": 43042
    },
    {
      "number": 15,
      "timestamp": 1752037224,
      "type": "loss",
      "variant": "normal",
      "calculation": 43027
    },
    {
      "number": 24,
      "timestamp": 1752038904,
      "type": "gain",
      "variant": "normal",
      "calculation": 43051
    },
    {
      "number": 45,
      "timestamp": 1752044423,
      "type": "gain",
      "variant": "volatile",
      "calculation": 43096
    },
    {
      "number": 26,
      "timestamp": 1752049135,
      "type": "gain",
      "variant": "volatile",
      "calculation": 43122
    },
    {
      "number": 23,
      "timestamp": 1752054177,
      "type": "gain",
      "variant": "normal",
      "calculation": 43145
    },
    {
      "number": 5,
      "timestamp": 1752055201,
      "type": "loss",
      "variant": "normal",
      "calculation": 43140
    },
    {
      "number": 22,
      "timestamp": 1752057957,
      "type": "gain",
      "variant": "normal",
      "calculation": 43162
    },
    {
      "number": 29,
      "timestamp": 1752060535,
      "type": "gain",
      "variant": "volatile",
      "calculation": 43191
    },
    {
      "number": 50,
      "timestamp": 1752062153,
      "type": "gain",
      "variant": "volatile",
      "calculation": 43241
    },
    {
      "number": 29,
      "timestamp": 1752066532,
      "type": "gain",
      "variant": "normal",
      "calculation": 43270
    },
    {
      "number": 41,
      "timestamp": 1752068624,
      "type": "gain",
      "variant": "normal",
      "calculation": 43311
    },
    {
      "number": 46,
      "timestamp": 1752071740,
      "type": "gain",
      "variant": "normal",
      "calculation": 43357
    }
  ]
}
