{
  "current": {
    "number": 66,
    "timestamp": 1753097481,
    "type": "gain",
    "variant": "normal"
  },
  "total": {
    "loss": 139,
    "gain": 285,
    "loss_count": 4461,
    "gain_count": 3042,
    "calculation": -374702
  },
  "old": [
    {
      "number": 139,
      "timestamp": 1753094635,
      "type": "loss",
      "variant": "normal",
      "calculation": -374987
    },
    {
      "number": 219,
      "timestamp": 1753096450,
      "type": "gain",
      "variant": "normal",
      "calculation": -374768
    }
  ]
}
