{
  "current": {
    "number": 74,
    "timestamp": 1777059611,
    "type": "loss",
    "variant": "normal"
  },
  "total": {
    "loss": 300,
    "gain": 198,
    "loss_count": 6666,
    "gain_count": 4243,
    "calculation": -125989
  },
  "old": [
    {
      "number": 43,
      "timestamp": 1776995658,
      "type": "gain",
      "variant": "normal",
      "calculation": -125844
    },
    {
      "number": 73,
      "timestamp": 1777005913,
      "type": "loss",
      "variant": "normal",
      "calculation": -125917
    },
    {
      "number": 16,
      "timestamp": 1777012152,
      "type": "loss",
      "variant": "volatile",
      "calculation": -125933
    },
    {
      "number": 45,
      "timestamp": 1777019454,
      "type": "loss",
      "variant": "normal",
      "calculation": -125978
    },
    {
      "number": 92,
      "timestamp": 1777025269,
      "type": "loss",
      "variant": "normal",
      "calculation": -126070
    },
    {
      "number": 77,
      "timestamp": 1777032541,
      "type": "gain",
      "variant": "normal",
      "calculation": -125993
    },
    {
      "number": 29,
      "timestamp": 1777039398,
      "type": "gain",
      "variant": "normal",
      "calculation": -125964
    },
    {
      "number": 49,
      "timestamp": 1777050727,
      "type": "gain",
      "variant": "normal",
      "calculation": -125915
    }
  ]
}
