{
  "current": {
    "number": 356,
    "timestamp": 1752898686,
    "type": "loss",
    "variant": "normal"
  },
  "total": {
    "loss": 10773,
    "gain": 7022,
    "loss_count": 4384,
    "gain_count": 2989,
    "calculation": -367762
  },
  "old": [
    {
      "number": 401,
      "timestamp": 1752770850,
      "type": "loss",
      "variant": "normal",
      "calculation": -364412
    },
    {
      "number": 191,
      "timestamp": 1752771619,
      "type": "loss",
      "variant": "volatile",
      "calculation": -364603
    },
    {
      "number": 16,
      "timestamp": 1752773056,
      "type": "loss",
      "variant": "volatile",
      "calculation": -364619
    },
    {
      "number": 100,
      "timestamp": 1752774090,
      "type": "gain",
      "variant": "volatile",
      "calculation": -364519
    },
    {
      "number": 335,
      "timestamp": 1752775132,
      "type": "gain",
      "variant": "normal",
      "calculation": -364184
    },
    {
      "number": 436,
      "timestamp": 1752779583,
      "type": "gain",
      "variant": "normal",
      "calculation": -363748
    },
    {
      "number": 356,
      "timestamp": 1752781647,
      "type": "gain",
      "variant": "volatile",
      "calculation": -363392
    },
    {
      "number": 160,
      "timestamp": 1752782071,
      "type": "gain",
      "variant": "normal",
      "calculation": -363232
    },
    {
      "number": 387,
      "timestamp": 1752783117,
      "type": "loss",
      "variant": "normal",
      "calculation": -363619
    },
    {
      "number": 361,
      "timestamp": 1752784478,
      "type": "loss",
      "variant": "volatile",
      "calculation": -363980
    },
    {
      "number": 186,
      "timestamp": 1752785826,
      "type": "loss",
      "variant": "volatile",
      "calculation": -364166
    },
    {
      "number": 127,
      "timestamp": 1752786978,
      "type": "loss",
      "variant": "volatile",
      "calculation": -364293
    },
    {
      "number": 382,
      "timestamp": 1752787986,
      "type": "loss",
      "variant": "normal",
      "calculation": -364675
    },
    {
      "number": 86,
      "timestamp": 1752789127,
      "type": "loss",
      "variant": "normal",
      "calculation": -364761
    },
    {
      "number": 94,
      "timestamp": 1752790876,
      "type": "gain",
      "variant": "volatile",
      "calculation": -364667
    },
    {
      "number": 357,
      "timestamp": 1752792078,
      "type": "gain",
      "variant": "normal",
      "calculation": -364310
    },
    {
      "number": 301,
      "timestamp": 1752792760,
      "type": "loss",
      "variant": "normal",
      "calculation": -364611
    },
    {
      "number": 253,
      "timestamp": 1752794595,
      "type": "loss",
      "variant": "normal",
      "calculation": -364864
    },
    {
      "number": 459,
      "timestamp": 1752796111,
      "type": "loss",
      "variant": "volatile",
      "calculation": -365323
    },
    {
      "number": 416,
      "timestamp": 1752796534,
      "type": "gain",
      "variant": "volatile",
      "calculation": -364907
    },
    {
      "number": 58,
      "timestamp": 1752800862,
      "type": "loss",
      "variant": "normal",
      "calculation": -364965
    },
    {
      "number": 332,
      "timestamp": 1752807933,
      "type": "loss",
      "variant": "normal",
      "calculation": -365297
    },
    {
      "number": 184,
      "timestamp": 1752811460,
      "type": "loss",
      "variant": "normal",
      "calculation": -365481
    },
    {
      "number": 142,
      "timestamp": 1752814069,
      "type": "loss",
      "variant": "normal",
      "calculation": -365623
    },
    {
      "number": 48,
      "timestamp": 1752817404,
      "type": "gain",
      "variant": "normal",
      "calculation": -365575
    },
    {
      "number": 53,
      "timestamp": 1752819617,
      "type": "loss",
      "variant": "normal",
      "calculation": -365628
    },
    {
      "number": 411,
      "timestamp": 1752821487,
      "type": "loss",
      "variant": "volatile",
      "calculation": -366039
    },
    {
      "number": 120,
      "timestamp": 1752823998,
      "type": "gain",
      "variant": "normal",
      "calculation": -365919
    },
    {
      "number": 325,
      "timestamp": 1752825395,
      "type": "loss",
      "variant": "volatile",
      "calculation": -366244
    },
    {
      "number": 267,
      "timestamp": 1752826892,
      "type": "loss",
      "variant": "volatile",
      "calculation": -366511
    },
    {
      "number": 28,
      "timestamp": 1752828412,
      "type": "gain",
      "variant": "normal",
      "calculation": -366483
    },
    {
      "number": 469,
      "timestamp": 1752832640,
      "type": "loss",
      "variant": "volatile",
      "calculation": -366952
    },
    {
      "number": 37,
      "timestamp": 1752833973,
      "type": "gain",
      "variant": "normal",
      "calculation": -366915
    },
    {
      "number": 367,
      "timestamp": 1752835463,
      "type": "loss",
      "variant": "normal",
      "calculation": -367282
    },
    {
      "number": 223,
      "timestamp": 1752837243,
      "type": "gain",
      "variant": "volatile",
      "calculation": -367059
    },
    {
      "number": 224,
      "timestamp": 1752838194,
      "type": "gain",
      "variant": "normal",
      "calculation": -366835
    },
    {
      "number": 205,
      "timestamp": 1752838978,
      "type": "gain",
      "variant": "volatile",
      "calculation": -366630
    },
    {
      "number": 300,
      "timestamp": 1752839940,
      "type": "loss",
      "variant": "normal",
      "calculation": -366930
    },
    {
      "number": 198,
      "timestamp": 1752842897,
      "type": "gain",
      "variant": "volatile",
      "calculation": -366732
    },
    {
      "number": 207,
      "timestamp": 1752845241,
      "type": "loss",
      "variant": "normal",
      "calculation": -366939
    },
    {
      "number": 484,
      "timestamp": 1752846824,
      "type": "gain",
      "variant": "normal",
      "calculation": -366455
    },
    {
      "number": 440,
      "timestamp": 1752850292,
      "type": "loss",
      "variant": "normal",
      "calculation": -366895
    },
    {
      "number": 62,
      "timestamp": 1752850713,
      "type": "gain",
      "variant": "normal",
      "calculation": -366833
    },
    {
      "number": 379,
      "timestamp": 1752852098,
      "type": "loss",
      "variant": "normal",
      "calculation": -367212
    },
    {
      "number": 388,
      "timestamp": 1752853191,
      "type": "gain",
      "variant": "normal",
      "calculation": -366824
    },
    {
      "number": 326,
      "timestamp": 1752854041,
      "type": "loss",
      "variant": "volatile",
      "calculation": -367150
    },
    {
      "number": 132,
      "timestamp": 1752855226,
      "type": "gain",
      "variant": "volatile",
      "calculation": -367018
    },
    {
      "number": 198,
      "timestamp": 1752858024,
      "type": "loss",
      "variant": "normal",
      "calculation": -367216
    },
    {
      "number": 29,
      "timestamp": 1752860551,
      "type": "loss",
      "variant": "normal",
      "calculation": -367245
    },
    {
      "number": 364,
      "timestamp": 1752861286,
      "type": "gain",
      "variant": "volatile",
      "calculation": -366881
    },
    {
      "number": 276,
      "timestamp": 1752862566,
      "type": "gain",
      "variant": "normal",
      "calculation": -366605
    },
    {
      "number": 345,
      "timestamp": 1752864391,
      "type": "gain",
      "variant": "normal",
      "calculation": -366260
    },
    {
      "number": 105,
      "timestamp": 1752865181,
      "type": "loss",
      "variant": "volatile",
      "calculation": -366365
    },
    {
      "number": 379,
      "timestamp": 1752866337,
      "type": "gain",
      "variant": "volatile",
      "calculation": -365986
    },
    {
      "number": 243,
      "timestamp": 1752867025,
      "type": "loss",
      "variant": "normal",
      "calculation": -366229
    },
    {
      "number": 86,
      "timestamp": 1752867671,
      "type": "loss",
      "variant": "volatile",
      "calculation": -366315
    },
    {
      "number": 52,
      "timestamp": 1752868123,
      "type": "gain",
      "variant": "volatile",
      "calculation": -366263
    },
    {
      "number": 280,
      "timestamp": 1752868550,
      "type": "loss",
      "variant": "normal",
      "calculation": -366543
    },
    {
      "number": 46,
      "timestamp": 1752869733,
      "type": "gain",
      "variant": "normal",
      "calculation": -366497
    },
    {
      "number": 424,
      "timestamp": 1752870987,
      "type": "gain",
      "variant": "volatile",
      "calculation": -366073
    },
    {
      "number": 372,
      "timestamp": 1752871769,
      "type": "loss",
      "variant": "normal",
      "calculation": -366445
    },
    {
      "number": 102,
      "timestamp": 1752872214,
      "type": "gain",
      "variant": "normal",
      "calculation": -366343
    },
    {
      "number": 340,
      "timestamp": 1752875091,
      "type": "loss",
      "variant": "normal",
      "calculation": -366683
    },
    {
      "number": 208,
      "timestamp": 1752875510,
      "type": "loss",
      "variant": "normal",
      "calculation": -366891
    },
    {
      "number": 342,
      "timestamp": 1752875928,
      "type": "gain",
      "variant": "volatile",
      "calculation": -366549
    },
    {
      "number": 156,
      "timestamp": 1752879585,
      "type": "loss",
      "variant": "normal",
      "calculation": -366705
    },
    {
      "number": 259,
      "timestamp": 1752881834,
      "type": "loss",
      "variant": "normal",
      "calculation": -366964
    },
    {
      "number": 39,
      "timestamp": 1752882448,
      "type": "loss",
      "variant": "volatile",
      "calculation": -367003
    },
    {
      "number": 288,
      "timestamp": 1752882888,
      "type": "gain",
      "variant": "normal",
      "calculation": -366715
    },
    {
      "number": 1,
      "timestamp": 1752886673,
      "type": "gain",
      "variant": "normal",
      "calculation": -366714
    },
    {
      "number": 212,
      "timestamp": 1752893366,
      "type": "loss",
      "variant": "volatile",
      "calculation": -366926
    },
    {
      "number": 480,
      "timestamp": 1752896688,
      "type": "loss",
      "variant": "volatile",
      "calculation": -367406
    }
  ]
}
