{
  "current": {
    "number": 64,
    "timestamp": 1758701594,
    "type": "loss",
    "variant": "volatile"
  },
  "total": {
    "loss": 2309,
    "gain": 1389,
    "loss_count": 908,
    "gain_count": 579,
    "calculation": -17567
  },
  "old": [
    {
      "number": 83,
      "timestamp": 1758581976,
      "type": "gain",
      "variant": "normal",
      "calculation": -16564
    },
    {
      "number": 21,
      "timestamp": 1758583111,
      "type": "gain",
      "variant": "volatile",
      "calculation": -16543
    },
    {
      "number": 36,
      "timestamp": 1758583706,
      "type": "loss",
      "variant": "normal",
      "calculation": -16579
    },
    {
      "number": 6,
      "timestamp": 1758585060,
      "type": "loss",
      "variant": "normal",
      "calculation": -16585
    },
    {
      "number": 8,
      "timestamp": 1758590320,
      "type": "loss",
      "variant": "volatile",
      "calculation": -16593
    },
    {
      "number": 75,
      "timestamp": 1758595006,
      "type": "gain",
      "variant": "normal",
      "calculation": -16518
    },
    {
      "number": 77,
      "timestamp": 1758599501,
      "type": "loss",
      "variant": "normal",
      "calculation": -16595
    },
    {
      "number": 7,
      "timestamp": 1758601330,
      "type": "loss",
      "variant": "normal",
      "calculation": -16602
    },
    {
      "number": 38,
      "timestamp": 1758602830,
      "type": "loss",
      "variant": "normal",
      "calculation": -16640
    },
    {
      "number": 8,
      "timestamp": 1758604200,
      "type": "gain",
      "variant": "normal",
      "calculation": -16632
    },
    {
      "number": 51,
      "timestamp": 1758606057,
      "type": "loss",
      "variant": "volatile",
      "calculation": -16683
    },
    {
      "number": 87,
      "timestamp": 1758606474,
      "type": "gain",
      "variant": "normal",
      "calculation": -16596
    },
    {
      "number": 24,
      "timestamp": 1758608243,
      "type": "loss",
      "variant": "normal",
      "calculation": -16620
    },
    {
      "number": 71,
      "timestamp": 1758609856,
      "type": "loss",
      "variant": "normal",
      "calculation": -16691
    },
    {
      "number": 11,
      "timestamp": 1758610502,
      "type": "gain",
      "variant": "normal",
      "calculation": -16680
    },
    {
      "number": 42,
      "timestamp": 1758611518,
      "type": "loss",
      "variant": "normal",
      "calculation": -16722
    },
    {
      "number": 14,
      "timestamp": 1758612524,
      "type": "loss",
      "variant": "volatile",
      "calculation": -16736
    },
    {
      "number": 13,
      "timestamp": 1758613122,
      "type": "loss",
      "variant": "normal",
      "calculation": -16749
    },
    {
      "number": 56,
      "timestamp": 1758613550,
      "type": "loss",
      "variant": "volatile",
      "calculation": -16805
    },
    {
      "number": 12,
      "timestamp": 1758614388,
      "type": "gain",
      "variant": "volatile",
      "calculation": -16793
    },
    {
      "number": 57,
      "timestamp": 1758616112,
      "type": "loss",
      "variant": "normal",
      "calculation": -16850
    },
    {
      "number": 16,
      "timestamp": 1758617167,
      "type": "gain",
      "variant": "normal",
      "calculation": -16834
    },
    {
      "number": 5,
      "timestamp": 1758621375,
      "type": "loss",
      "variant": "normal",
      "calculation": -16839
    },
    {
      "number": 14,
      "timestamp": 1758622457,
      "type": "loss",
      "variant": "normal",
      "calculation": -16853
    },
    {
      "number": 44,
      "timestamp": 1758624319,
      "type": "loss",
      "variant": "volatile",
      "calculation": -16897
    },
    {
      "number": 17,
      "timestamp": 1758624747,
      "type": "gain",
      "variant": "normal",
      "calculation": -16880
    },
    {
      "number": 18,
      "timestamp": 1758625167,
      "type": "gain",
      "variant": "normal",
      "calculation": -16862
    },
    {
      "number": 9,
      "timestamp": 1758626228,
      "type": "loss",
      "variant": "volatile",
      "calculation": -16871
    },
    {
      "number": 11,
      "timestamp": 1758626869,
      "type": "loss",
      "variant": "normal",
      "calculation": -16882
    },
    {
      "number": 4,
      "timestamp": 1758627409,
      "type": "loss",
      "variant": "normal",
      "calculation": -16886
    },
    {
      "number": 79,
      "timestamp": 1758627817,
      "type": "gain",
      "variant": "normal",
      "calculation": -16807
    },
    {
      "number": 7,
      "timestamp": 1758628249,
      "type": "gain",
      "variant": "normal",
      "calculation": -16800
    },
    {
      "number": 96,
      "timestamp": 1758628673,
      "type": "gain",
      "variant": "volatile",
      "calculation": -16704
    },
    {
      "number": 65,
      "timestamp": 1758630937,
      "type": "gain",
      "variant": "normal",
      "calculation": -16639
    },
    {
      "number": 14,
      "timestamp": 1758632778,
      "type": "loss",
      "variant": "normal",
      "calculation": -16653
    },
    {
      "number": 81,
      "timestamp": 1758634542,
      "type": "loss",
      "variant": "volatile",
      "calculation": -16734
    },
    {
      "number": 48,
      "timestamp": 1758635286,
      "type": "gain",
      "variant": "normal",
      "calculation": -16686
    },
    {
      "number": 30,
      "timestamp": 1758635724,
      "type": "loss",
      "variant": "normal",
      "calculation": -16716
    },
    {
      "number": 90,
      "timestamp": 1758636744,
      "type": "loss",
      "variant": "volatile",
      "calculation": -16806
    },
    {
      "number": 48,
      "timestamp": 1758637993,
      "type": "loss",
      "variant": "normal",
      "calculation": -16854
    },
    {
      "number": 80,
      "timestamp": 1758638772,
      "type": "loss",
      "variant": "normal",
      "calculation": -16934
    },
    {
      "number": 14,
      "timestamp": 1758639666,
      "type": "loss",
      "variant": "normal",
      "calculation": -16948
    },
    {
      "number": 19,
      "timestamp": 1758642361,
      "type": "gain",
      "variant": "volatile",
      "calculation": -16929
    },
    {
      "number": 75,
      "timestamp": 1758642806,
      "type": "loss",
      "variant": "normal",
      "calculation": -17004
    },
    {
      "number": 68,
      "timestamp": 1758643256,
      "type": "loss",
      "variant": "normal",
      "calculation": -17072
    },
    {
      "number": 100,
      "timestamp": 1758645043,
      "type": "loss",
      "variant": "normal",
      "calculation": -17172
    },
    {
      "number": 63,
      "timestamp": 1758646476,
      "type": "loss",
      "variant": "normal",
      "calculation": -17235
    },
    {
      "number": 12,
      "timestamp": 1758647252,
      "type": "gain",
      "variant": "normal",
      "calculation": -17223
    },
    {
      "number": 65,
      "timestamp": 1758648337,
      "type": "loss",
      "variant": "volatile",
      "calculation": -17288
    },
    {
      "number": 12,
      "timestamp": 1758649635,
      "type": "loss",
      "variant": "normal",
      "calculation": -17300
    },
    {
      "number": 32,
      "timestamp": 1758650078,
      "type": "loss",
      "variant": "normal",
      "calculation": -17332
    },
    {
      "number": 6,
      "timestamp": 1758651330,
      "type": "loss",
      "variant": "volatile",
      "calculation": -17338
    },
    {
      "number": 12,
      "timestamp": 1758652948,
      "type": "loss",
      "variant": "volatile",
      "calculation": -17350
    },
    {
      "number": 50,
      "timestamp": 1758655619,
      "type": "loss",
      "variant": "normal",
      "calculation": -17400
    },
    {
      "number": 11,
      "timestamp": 1758656149,
      "type": "gain",
      "variant": "volatile",
      "calculation": -17389
    },
    {
      "number": 21,
      "timestamp": 1758656585,
      "type": "loss",
      "variant": "normal",
      "calculation": -17410
    },
    {
      "number": 59,
      "timestamp": 1758657028,
      "type": "loss",
      "variant": "volatile",
      "calculation": -17469
    },
    {
      "number": 22,
      "timestamp": 1758657458,
      "type": "gain",
      "variant": "normal",
      "calculation": -17447
    },
    {
      "number": 2,
      "timestamp": 1758658682,
      "type": "loss",
      "variant": "normal",
      "calculation": -17449
    },
    {
      "number": 79,
      "timestamp": 1758660179,
      "type": "loss",
      "variant": "normal",
      "calculation": -17528
    },
    {
      "number": 53,
      "timestamp": 1758660608,
      "type": "loss",
      "variant": "normal",
      "calculation": -17581
    },
    {
      "number": 93,
      "timestamp": 1758661028,
      "type": "gain",
      "variant": "normal",
      "calculation": -17488
    },
    {
      "number": 1,
      "timestamp": 1758662007,
      "type": "loss",
      "variant": "normal",
      "calculation": -17489
    },
    {
      "number": 77,
      "timestamp": 1758662817,
      "type": "gain",
      "variant": "normal",
      "calculation": -17412
    },
    {
      "number": 16,
      "timestamp": 1758663723,
      "type": "gain",
      "variant": "volatile",
      "calculation": -17396
    },
    {
      "number": 76,
      "timestamp": 1758664559,
      "type": "loss",
      "variant": "volatile",
      "calculation": -17472
    },
    {
      "number": 29,
      "timestamp": 1758666587,
      "type": "gain",
      "variant": "volatile",
      "calculation": -17443
    },
    {
      "number": 50,
      "timestamp": 1758667190,
      "type": "gain",
      "variant": "normal",
      "calculation": -17393
    },
    {
      "number": 64,
      "timestamp": 1758668038,
      "type": "loss",
      "variant": "normal",
      "calculation": -17457
    },
    {
      "number": 90,
      "timestamp": 1758668867,
      "type": "gain",
      "variant": "normal",
      "calculation": -17367
    },
    {
      "number": 22,
      "timestamp": 1758670251,
      "type": "loss",
      "variant": "volatile",
      "calculation": -17389
    },
    {
      "number": 42,
      "timestamp": 1758670749,
      "type": "loss",
      "variant": "normal",
      "calculation": -17431
    },
    {
      "number": 86,
      "timestamp": 1758671626,
      "type": "loss",
      "variant": "volatile",
      "calculation": -17517
    },
    {
      "number": 29,
      "timestamp": 1758674485,
      "type": "gain",
      "variant": "normal",
      "calculation": -17488
    },
    {
      "number": 4,
      "timestamp": 1758685808,
      "type": "loss",
      "variant": "normal",
      "calculation": -17492
    },
    {
      "number": 48,
      "timestamp": 1758686221,
      "type": "loss",
      "variant": "normal",
      "calculation": -17540
    },
    {
      "number": 38,
      "timestamp": 1758688562,
      "type": "gain",
      "variant": "normal",
      "calculation": -17502
    },
    {
      "number": 62,
      "timestamp": 1758690063,
      "type": "loss",
      "variant": "normal",
      "calculation": -17564
    },
    {
      "number": 12,
      "timestamp": 1758691398,
      "type": "loss",
      "variant": "volatile",
      "calculation": -17576
    },
    {
      "number": 80,
      "timestamp": 1758692196,
      "type": "loss",
      "variant": "normal",
      "calculation": -17656
    },
    {
      "number": 56,
      "timestamp": 1758693070,
      "type": "loss",
      "variant": "normal",
      "calculation": -17712
    },
    {
      "number": 88,
      "timestamp": 1758693480,
      "type": "gain",
      "variant": "normal",
      "calculation": -17624
    },
    {
      "number": 35,
      "timestamp": 1758695204,
      "type": "gain",
      "variant": "normal",
      "calculation": -17589
    },
    {
      "number": 51,
      "timestamp": 1758696968,
      "type": "gain",
      "variant": "normal",
      "calculation": -17538
    },
    {
      "number": 51,
      "timestamp": 1758699563,
      "type": "loss",
      "variant": "volatile",
      "calculation": -17589
    },
    {
      "number": 86,
      "timestamp": 1758700439,
      "type": "gain",
      "variant": "normal",
      "calculation": -17503
    }
  ]
}
