{
  "current": {
    "number": 311,
    "timestamp": 1756714858,
    "type": "loss",
    "variant": "normal"
  },
  "total": {
    "loss": 12476,
    "gain": 9097,
    "loss_count": 5873,
    "gain_count": 4012,
    "calculation": -488696
  },
  "old": [
    {
      "number": 123,
      "timestamp": 1756613783,
      "type": "loss",
      "variant": "volatile",
      "calculation": -485440
    },
    {
      "number": 384,
      "timestamp": 1756614893,
      "type": "gain",
      "variant": "normal",
      "calculation": -485056
    },
    {
      "number": 490,
      "timestamp": 1756615504,
      "type": "loss",
      "variant": "volatile",
      "calculation": -485546
    },
    {
      "number": 489,
      "timestamp": 1756616331,
      "type": "gain",
      "variant": "normal",
      "calculation": -485057
    },
    {
      "number": 124,
      "timestamp": 1756617472,
      "type": "gain",
      "variant": "normal",
      "calculation": -484933
    },
    {
      "number": 211,
      "timestamp": 1756618909,
      "type": "gain",
      "variant": "normal",
      "calculation": -484722
    },
    {
      "number": 268,
      "timestamp": 1756621038,
      "type": "gain",
      "variant": "volatile",
      "calculation": -484454
    },
    {
      "number": 13,
      "timestamp": 1756622488,
      "type": "gain",
      "variant": "normal",
      "calculation": -484441
    },
    {
      "number": 475,
      "timestamp": 1756623074,
      "type": "gain",
      "variant": "normal",
      "calculation": -483966
    },
    {
      "number": 272,
      "timestamp": 1756624572,
      "type": "loss",
      "variant": "normal",
      "calculation": -484238
    },
    {
      "number": 99,
      "timestamp": 1756626162,
      "type": "gain",
      "variant": "volatile",
      "calculation": -484139
    },
    {
      "number": 88,
      "timestamp": 1756626595,
      "type": "loss",
      "variant": "normal",
      "calculation": -484227
    },
    {
      "number": 355,
      "timestamp": 1756627003,
      "type": "loss",
      "variant": "volatile",
      "calculation": -484582
    },
    {
      "number": 263,
      "timestamp": 1756628246,
      "type": "loss",
      "variant": "normal",
      "calculation": -484845
    },
    {
      "number": 437,
      "timestamp": 1756629271,
      "type": "gain",
      "variant": "volatile",
      "calculation": -484408
    },
    {
      "number": 136,
      "timestamp": 1756629905,
      "type": "loss",
      "variant": "normal",
      "calculation": -484544
    },
    {
      "number": 465,
      "timestamp": 1756630326,
      "type": "loss",
      "variant": "normal",
      "calculation": -485009
    },
    {
      "number": 195,
      "timestamp": 1756632567,
      "type": "loss",
      "variant": "normal",
      "calculation": -485204
    },
    {
      "number": 333,
      "timestamp": 1756633494,
      "type": "loss",
      "variant": "volatile",
      "calculation": -485537
    },
    {
      "number": 17,
      "timestamp": 1756634346,
      "type": "loss",
      "variant": "normal",
      "calculation": -485554
    },
    {
      "number": 203,
      "timestamp": 1756636926,
      "type": "gain",
      "variant": "volatile",
      "calculation": -485351
    },
    {
      "number": 167,
      "timestamp": 1756637352,
      "type": "loss",
      "variant": "volatile",
      "calculation": -485518
    },
    {
      "number": 125,
      "timestamp": 1756637777,
      "type": "loss",
      "variant": "normal",
      "calculation": -485643
    },
    {
      "number": 223,
      "timestamp": 1756638619,
      "type": "gain",
      "variant": "volatile",
      "calculation": -485420
    },
    {
      "number": 415,
      "timestamp": 1756639346,
      "type": "loss",
      "variant": "volatile",
      "calculation": -485835
    },
    {
      "number": 498,
      "timestamp": 1756639761,
      "type": "gain",
      "variant": "normal",
      "calculation": -485337
    },
    {
      "number": 381,
      "timestamp": 1756641123,
      "type": "loss",
      "variant": "normal",
      "calculation": -485718
    },
    {
      "number": 191,
      "timestamp": 1756641549,
      "type": "loss",
      "variant": "normal",
      "calculation": -485909
    },
    {
      "number": 361,
      "timestamp": 1756643864,
      "type": "loss",
      "variant": "normal",
      "calculation": -486270
    },
    {
      "number": 374,
      "timestamp": 1756645355,
      "type": "gain",
      "variant": "normal",
      "calculation": -485896
    },
    {
      "number": 290,
      "timestamp": 1756646893,
      "type": "loss",
      "variant": "volatile",
      "calculation": -486186
    },
    {
      "number": 423,
      "timestamp": 1756647955,
      "type": "loss",
      "variant": "normal",
      "calculation": -486609
    },
    {
      "number": 11,
      "timestamp": 1756649893,
      "type": "loss",
      "variant": "volatile",
      "calculation": -486620
    },
    {
      "number": 250,
      "timestamp": 1756650669,
      "type": "gain",
      "variant": "volatile",
      "calculation": -486370
    },
    {
      "number": 290,
      "timestamp": 1756651240,
      "type": "loss",
      "variant": "volatile",
      "calculation": -486660
    },
    {
      "number": 284,
      "timestamp": 1756651654,
      "type": "loss",
      "variant": "volatile",
      "calculation": -486944
    },
    {
      "number": 206,
      "timestamp": 1756652925,
      "type": "loss",
      "variant": "normal",
      "calculation": -487150
    },
    {
      "number": 446,
      "timestamp": 1756654516,
      "type": "gain",
      "variant": "normal",
      "calculation": -486704
    },
    {
      "number": 87,
      "timestamp": 1756654945,
      "type": "gain",
      "variant": "normal",
      "calculation": -486617
    },
    {
      "number": 407,
      "timestamp": 1756655377,
      "type": "gain",
      "variant": "normal",
      "calculation": -486210
    },
    {
      "number": 217,
      "timestamp": 1756655789,
      "type": "gain",
      "variant": "normal",
      "calculation": -485993
    },
    {
      "number": 146,
      "timestamp": 1756656937,
      "type": "gain",
      "variant": "normal",
      "calculation": -485847
    },
    {
      "number": 144,
      "timestamp": 1756658097,
      "type": "gain",
      "variant": "volatile",
      "calculation": -485703
    },
    {
      "number": 78,
      "timestamp": 1756658764,
      "type": "loss",
      "variant": "normal",
      "calculation": -485781
    },
    {
      "number": 478,
      "timestamp": 1756659177,
      "type": "loss",
      "variant": "normal",
      "calculation": -486259
    },
    {
      "number": 495,
      "timestamp": 1756662326,
      "type": "loss",
      "variant": "normal",
      "calculation": -486754
    },
    {
      "number": 83,
      "timestamp": 1756662739,
      "type": "loss",
      "variant": "volatile",
      "calculation": -486837
    },
    {
      "number": 1,
      "timestamp": 1756663152,
      "type": "loss",
      "variant": "volatile",
      "calculation": -486838
    },
    {
      "number": 462,
      "timestamp": 1756664789,
      "type": "loss",
      "variant": "volatile",
      "calculation": -487300
    },
    {
      "number": 128,
      "timestamp": 1756665810,
      "type": "loss",
      "variant": "volatile",
      "calculation": -487428
    },
    {
      "number": 138,
      "timestamp": 1756666274,
      "type": "loss",
      "variant": "volatile",
      "calculation": -487566
    },
    {
      "number": 449,
      "timestamp": 1756666689,
      "type": "gain",
      "variant": "normal",
      "calculation": -487117
    },
    {
      "number": 188,
      "timestamp": 1756668218,
      "type": "gain",
      "variant": "normal",
      "calculation": -486929
    },
    {
      "number": 8,
      "timestamp": 1756668643,
      "type": "loss",
      "variant": "normal",
      "calculation": -486937
    },
    {
      "number": 440,
      "timestamp": 1756669577,
      "type": "loss",
      "variant": "normal",
      "calculation": -487377
    },
    {
      "number": 2,
      "timestamp": 1756669998,
      "type": "loss",
      "variant": "normal",
      "calculation": -487379
    },
    {
      "number": 22,
      "timestamp": 1756671778,
      "type": "loss",
      "variant": "normal",
      "calculation": -487401
    },
    {
      "number": 63,
      "timestamp": 1756672998,
      "type": "gain",
      "variant": "normal",
      "calculation": -487338
    },
    {
      "number": 303,
      "timestamp": 1756673404,
      "type": "loss",
      "variant": "volatile",
      "calculation": -487641
    },
    {
      "number": 16,
      "timestamp": 1756675592,
      "type": "gain",
      "variant": "normal",
      "calculation": -487625
    },
    {
      "number": 28,
      "timestamp": 1756676095,
      "type": "loss",
      "variant": "normal",
      "calculation": -487653
    },
    {
      "number": 431,
      "timestamp": 1756676949,
      "type": "loss",
      "variant": "normal",
      "calculation": -488084
    },
    {
      "number": 120,
      "timestamp": 1756677372,
      "type": "loss",
      "variant": "normal",
      "calculation": -488204
    },
    {
      "number": 234,
      "timestamp": 1756678357,
      "type": "loss",
      "variant": "normal",
      "calculation": -488438
    },
    {
      "number": 257,
      "timestamp": 1756679411,
      "type": "gain",
      "variant": "normal",
      "calculation": -488181
    },
    {
      "number": 360,
      "timestamp": 1756680053,
      "type": "loss",
      "variant": "normal",
      "calculation": -488541
    },
    {
      "number": 282,
      "timestamp": 1756683256,
      "type": "loss",
      "variant": "volatile",
      "calculation": -488823
    },
    {
      "number": 435,
      "timestamp": 1756683709,
      "type": "loss",
      "variant": "volatile",
      "calculation": -489258
    },
    {
      "number": 470,
      "timestamp": 1756684125,
      "type": "loss",
      "variant": "volatile",
      "calculation": -489728
    },
    {
      "number": 244,
      "timestamp": 1756684548,
      "type": "gain",
      "variant": "normal",
      "calculation": -489484
    },
    {
      "number": 456,
      "timestamp": 1756695540,
      "type": "loss",
      "variant": "normal",
      "calculation": -489940
    },
    {
      "number": 81,
      "timestamp": 1756698665,
      "type": "loss",
      "variant": "normal",
      "calculation": -490021
    },
    {
      "number": 182,
      "timestamp": 1756700299,
      "type": "loss",
      "variant": "volatile",
      "calculation": -490203
    },
    {
      "number": 5,
      "timestamp": 1756701768,
      "type": "loss",
      "variant": "volatile",
      "calculation": -490208
    },
    {
      "number": 99,
      "timestamp": 1756702401,
      "type": "loss",
      "variant": "normal",
      "calculation": -490307
    },
    {
      "number": 450,
      "timestamp": 1756704297,
      "type": "gain",
      "variant": "normal",
      "calculation": -489857
    },
    {
      "number": 308,
      "timestamp": 1756705650,
      "type": "gain",
      "variant": "normal",
      "calculation": -489549
    },
    {
      "number": 404,
      "timestamp": 1756707444,
      "type": "gain",
      "variant": "normal",
      "calculation": -489145
    },
    {
      "number": 102,
      "timestamp": 1756709270,
      "type": "gain",
      "variant": "normal",
      "calculation": -489043
    },
    {
      "number": 239,
      "timestamp": 1756709923,
      "type": "gain",
      "variant": "normal",
      "calculation": -488804
    },
    {
      "number": 417,
      "timestamp": 1756711194,
      "type": "gain",
      "variant": "normal",
      "calculation": -488387
    },
    {
      "number": 463,
      "timestamp": 1756712548,
      "type": "loss",
      "variant": "normal",
      "calculation": -488850
    },
    {
      "number": 208,
      "timestamp": 1756712965,
      "type": "gain",
      "variant": "volatile",
      "calculation": -488642
    },
    {
      "number": 257,
      "timestamp": 1756713381,
      "type": "gain",
      "variant": "normal",
      "calculation": -488385
    }
  ]
}
