{
  "current": {
    "number": 350,
    "timestamp": 1748595275,
    "type": "gain",
    "variant": "normal"
  },
  "total": {
    "loss": 5258,
    "gain": 2016,
    "loss_count": 2659,
    "gain_count": 1871,
    "calculation": -216444
  },
  "old": [
    {
      "number": 241,
      "timestamp": 1748547103,
      "type": "gain",
      "variant": "normal",
      "calculation": -212961
    },
    {
      "number": 52,
      "timestamp": 1748548042,
      "type": "loss",
      "variant": "normal",
      "calculation": -213013
    },
    {
      "number": 331,
      "timestamp": 1748548468,
      "type": "loss",
      "variant": "normal",
      "calculation": -213344
    },
    {
      "number": 285,
      "timestamp": 1748549526,
      "type": "loss",
      "variant": "normal",
      "calculation": -213629
    },
    {
      "number": 200,
      "timestamp": 1748550727,
      "type": "loss",
      "variant": "normal",
      "calculation": -213829
    },
    {
      "number": 176,
      "timestamp": 1748551457,
      "type": "gain",
      "variant": "volatile",
      "calculation": -213653
    },
    {
      "number": 94,
      "timestamp": 1748552325,
      "type": "gain",
      "variant": "normal",
      "calculation": -213559
    },
    {
      "number": 30,
      "timestamp": 1748553504,
      "type": "loss",
      "variant": "normal",
      "calculation": -213589
    },
    {
      "number": 478,
      "timestamp": 1748555334,
      "type": "loss",
      "variant": "normal",
      "calculation": -214067
    },
    {
      "number": 264,
      "timestamp": 1748558056,
      "type": "gain",
      "variant": "normal",
      "calculation": -213803
    },
    {
      "number": 359,
      "timestamp": 1748558791,
      "type": "loss",
      "variant": "volatile",
      "calculation": -214162
    },
    {
      "number": 176,
      "timestamp": 1748559217,
      "type": "loss",
      "variant": "normal",
      "calculation": -214338
    },
    {
      "number": 138,
      "timestamp": 1748560049,
      "type": "loss",
      "variant": "volatile",
      "calculation": -214476
    },
    {
      "number": 113,
      "timestamp": 1748561178,
      "type": "gain",
      "variant": "normal",
      "calculation": -214363
    },
    {
      "number": 286,
      "timestamp": 1748562354,
      "type": "gain",
      "variant": "normal",
      "calculation": -214077
    },
    {
      "number": 34,
      "timestamp": 1748562775,
      "type": "loss",
      "variant": "normal",
      "calculation": -214111
    },
    {
      "number": 469,
      "timestamp": 1748563199,
      "type": "loss",
      "variant": "normal",
      "calculation": -214580
    },
    {
      "number": 417,
      "timestamp": 1748569895,
      "type": "loss",
      "variant": "volatile",
      "calculation": -214997
    },
    {
      "number": 340,
      "timestamp": 1748577629,
      "type": "loss",
      "variant": "normal",
      "calculation": -215337
    },
    {
      "number": 440,
      "timestamp": 1748580426,
      "type": "loss",
      "variant": "volatile",
      "calculation": -215777
    },
    {
      "number": 185,
      "timestamp": 1748581977,
      "type": "loss",
      "variant": "normal",
      "calculation": -215962
    },
    {
      "number": 8,
      "timestamp": 1748584782,
      "type": "loss",
      "variant": "normal",
      "calculation": -215970
    },
    {
      "number": 317,
      "timestamp": 1748586703,
      "type": "loss",
      "variant": "normal",
      "calculation": -216287
    },
    {
      "number": 320,
      "timestamp": 1748588346,
      "type": "loss",
      "variant": "normal",
      "calculation": -216607
    },
    {
      "number": 348,
      "timestamp": 1748589589,
      "type": "loss",
      "variant": "normal",
      "calculation": -216955
    },
    {
      "number": 492,
      "timestamp": 1748590892,
      "type": "gain",
      "variant": "volatile",
      "calculation": -216463
    },
    {
      "number": 236,
      "timestamp": 1748591740,
      "type": "loss",
      "variant": "normal",
      "calculation": -216699
    },
    {
      "number": 70,
      "timestamp": 1748593038,
      "type": "loss",
      "variant": "normal",
      "calculation": -216769
    },
    {
      "number": 25,
      "timestamp": 1748594508,
      "type": "loss",
      "variant": "normal",
      "calculation": -216794
    }
  ]
}
